Metadata-Version: 1.0
Name: pscli
Version: 1.1.0
Summary: Unofficial Cisco Parstream Client with improved cli
Home-page: https://github.com/cs91chris/parstream-client
Author: cs91chris
Author-email: cs91chris@voidbrain.me
License: MIT
Platform: any
